{
    "commands": {
        "sort_names": "none",
        "collection_rank": 300000,
        "member_rank": 2000000
    },
    "data": {
        "collection_id": "arabic-999-club",
        "collection_name": "Arabic 999 Club",
        "collection_description": "Arabic numerals 000-999.",
        "collection_keywords": [
            "ens-clubs"
        ],
        "labels": [
            {
                "normalized_label": "٠٠٠"
            },
            {
                "normalized_label": "٠٠١"
            },
            {
                "normalized_label": "٠٠٢"
            },
            {
                "normalized_label": "٠٠٣"
            },
            {
                "normalized_label": "٠٠٤"
            },
            {
                "normalized_label": "٠٠٥"
            },
            {
                "normalized_label": "٠٠٦"
            },
            {
                "normalized_label": "٠٠٧"
            },
            {
                "normalized_label": "٠٠٨"
            },
            {
                "normalized_label": "٠٠٩"
            },
            {
                "normalized_label": "٠١٠"
            },
            {
                "normalized_label": "٠١٢"
            },
            {
                "normalized_label": "٠١١"
            },
            {
                "normalized_label": "٠١٣"
            },
            {
                "normalized_label": "٠١٤"
            },
            {
                "normalized_label": "٠١٥"
            },
            {
                "normalized_label": "٠١٦"
            },
            {
                "normalized_label": "٠١٧"
            },
            {
                "normalized_label": "٠١٨"
            },
            {
                "normalized_label": "٠١٩"
            },
            {
                "normalized_label": "٠٢٠"
            },
            {
                "normalized_label": "٠٢١"
            },
            {
                "normalized_label": "٠٢٢"
            },
            {
                "normalized_label": "٠٢٣"
            },
            {
                "normalized_label": "٠٢٤"
            },
            {
                "normalized_label": "٠٢٥"
            },
            {
                "normalized_label": "٠٢٦"
            },
            {
                "normalized_label": "٠٢٧"
            },
            {
                "normalized_label": "٠٢٨"
            },
            {
                "normalized_label": "٠٢٩"
            },
            {
                "normalized_label": "٠٣٠"
            },
            {
                "normalized_label": "٠٣١"
            },
            {
                "normalized_label": "٠٣٢"
            },
            {
                "normalized_label": "٠٣٣"
            },
            {
                "normalized_label": "٠٣٤"
            },
            {
                "normalized_label": "٠٣٥"
            },
            {
                "normalized_label": "٠٣٦"
            },
            {
                "normalized_label": "٠٣٧"
            },
            {
                "normalized_label": "٠٣٨"
            },
            {
                "normalized_label": "٠٣٩"
            },
            {
                "normalized_label": "٠٤٠"
            },
            {
                "normalized_label": "٠٤١"
            },
            {
                "normalized_label": "٠٤٢"
            },
            {
                "normalized_label": "٠٤٣"
            },
            {
                "normalized_label": "٠٤٤"
            },
            {
                "normalized_label": "٠٤٥"
            },
            {
                "normalized_label": "٠٤٦"
            },
            {
                "normalized_label": "٠٤٧"
            },
            {
                "normalized_label": "٠٤٨"
            },
            {
                "normalized_label": "٠٤٩"
            },
            {
                "normalized_label": "٠٥٠"
            },
            {
                "normalized_label": "٠٥١"
            },
            {
                "normalized_label": "٠٥٢"
            },
            {
                "normalized_label": "٠٥٣"
            },
            {
                "normalized_label": "٠٥٤"
            },
            {
                "normalized_label": "٠٥٥"
            },
            {
                "normalized_label": "٠٥٦"
            },
            {
                "normalized_label": "٠٥٧"
            },
            {
                "normalized_label": "٠٥٨"
            },
            {
                "normalized_label": "٠٥٩"
            },
            {
                "normalized_label": "٠٦٠"
            },
            {
                "normalized_label": "٠٦١"
            },
            {
                "normalized_label": "٠٦٢"
            },
            {
                "normalized_label": "٠٦٣"
            },
            {
                "normalized_label": "٠٦٤"
            },
            {
                "normalized_label": "٠٦٥"
            },
            {
                "normalized_label": "٠٦٦"
            },
            {
                "normalized_label": "٠٦٧"
            },
            {
                "normalized_label": "٠٦٨"
            },
            {
                "normalized_label": "٠٦٩"
            },
            {
                "normalized_label": "٠٧٠"
            },
            {
                "normalized_label": "٠٧١"
            },
            {
                "normalized_label": "٠٧٢"
            },
            {
                "normalized_label": "٠٧٣"
            },
            {
                "normalized_label": "٠٧٤"
            },
            {
                "normalized_label": "٠٧٥"
            },
            {
                "normalized_label": "٠٧٦"
            },
            {
                "normalized_label": "٠٧٧"
            },
            {
                "normalized_label": "٠٧٨"
            },
            {
                "normalized_label": "٠٧٩"
            },
            {
                "normalized_label": "٠٨٠"
            },
            {
                "normalized_label": "٠٨١"
            },
            {
                "normalized_label": "٠٨٢"
            },
            {
                "normalized_label": "٠٨٣"
            },
            {
                "normalized_label": "٠٨٤"
            },
            {
                "normalized_label": "٠٨٥"
            },
            {
                "normalized_label": "٠٨٦"
            },
            {
                "normalized_label": "٠٨٧"
            },
            {
                "normalized_label": "٠٨٨"
            },
            {
                "normalized_label": "٠٨٩"
            },
            {
                "normalized_label": "٠٩٠"
            },
            {
                "normalized_label": "٠٩١"
            },
            {
                "normalized_label": "٠٩٢"
            },
            {
                "normalized_label": "٠٩٣"
            },
            {
                "normalized_label": "٠٩٤"
            },
            {
                "normalized_label": "٠٩٥"
            },
            {
                "normalized_label": "٠٩٦"
            },
            {
                "normalized_label": "٠٩٧"
            },
            {
                "normalized_label": "٠٩٨"
            },
            {
                "normalized_label": "٠٩٩"
            },
            {
                "normalized_label": "١٠٠"
            },
            {
                "normalized_label": "١٠١"
            },
            {
                "normalized_label": "١٠٢"
            },
            {
                "normalized_label": "١٠٣"
            },
            {
                "normalized_label": "١٠٤"
            },
            {
                "normalized_label": "١٠٥"
            },
            {
                "normalized_label": "١٠٦"
            },
            {
                "normalized_label": "١٠٧"
            },
            {
                "normalized_label": "١٠٨"
            },
            {
                "normalized_label": "١٠٩"
            },
            {
                "normalized_label": "١١٠"
            },
            {
                "normalized_label": "١١١"
            },
            {
                "normalized_label": "١١٢"
            },
            {
                "normalized_label": "١١٣"
            },
            {
                "normalized_label": "١١٤"
            },
            {
                "normalized_label": "١١٥"
            },
            {
                "normalized_label": "١١٦"
            },
            {
                "normalized_label": "١١٧"
            },
            {
                "normalized_label": "١١٨"
            },
            {
                "normalized_label": "١١٩"
            },
            {
                "normalized_label": "١٢٠"
            },
            {
                "normalized_label": "١٢١"
            },
            {
                "normalized_label": "١٢٢"
            },
            {
                "normalized_label": "١٢٣"
            },
            {
                "normalized_label": "١٢٤"
            },
            {
                "normalized_label": "١٢٥"
            },
            {
                "normalized_label": "١٢٦"
            },
            {
                "normalized_label": "١٢٧"
            },
            {
                "normalized_label": "١٢٨"
            },
            {
                "normalized_label": "١٢٩"
            },
            {
                "normalized_label": "١٣٠"
            },
            {
                "normalized_label": "١٣١"
            },
            {
                "normalized_label": "١٣٢"
            },
            {
                "normalized_label": "١٣٣"
            },
            {
                "normalized_label": "١٣٤"
            },
            {
                "normalized_label": "١٣٥"
            },
            {
                "normalized_label": "١٣٦"
            },
            {
                "normalized_label": "١٣٧"
            },
            {
                "normalized_label": "١٣٨"
            },
            {
                "normalized_label": "١٣٩"
            },
            {
                "normalized_label": "١٤٠"
            },
            {
                "normalized_label": "١٤١"
            },
            {
                "normalized_label": "١٤٢"
            },
            {
                "normalized_label": "١٤٣"
            },
            {
                "normalized_label": "١٤٤"
            },
            {
                "normalized_label": "١٤٥"
            },
            {
                "normalized_label": "١٤٦"
            },
            {
                "normalized_label": "١٤٧"
            },
            {
                "normalized_label": "١٤٨"
            },
            {
                "normalized_label": "١٤٩"
            },
            {
                "normalized_label": "١٥٠"
            },
            {
                "normalized_label": "١٥١"
            },
            {
                "normalized_label": "١٥٢"
            },
            {
                "normalized_label": "١٥٣"
            },
            {
                "normalized_label": "١٥٤"
            },
            {
                "normalized_label": "١٥٥"
            },
            {
                "normalized_label": "١٥٦"
            },
            {
                "normalized_label": "١٥٧"
            },
            {
                "normalized_label": "١٥٨"
            },
            {
                "normalized_label": "١٥٩"
            },
            {
                "normalized_label": "١٦٠"
            },
            {
                "normalized_label": "١٦١"
            },
            {
                "normalized_label": "١٦٢"
            },
            {
                "normalized_label": "١٦٣"
            },
            {
                "normalized_label": "١٦٤"
            },
            {
                "normalized_label": "١٦٥"
            },
            {
                "normalized_label": "١٦٦"
            },
            {
                "normalized_label": "١٦٧"
            },
            {
                "normalized_label": "١٦٨"
            },
            {
                "normalized_label": "١٦٩"
            },
            {
                "normalized_label": "١٧٠"
            },
            {
                "normalized_label": "١٧١"
            },
            {
                "normalized_label": "١٧٢"
            },
            {
                "normalized_label": "١٧٣"
            },
            {
                "normalized_label": "١٧٤"
            },
            {
                "normalized_label": "١٧٥"
            },
            {
                "normalized_label": "١٧٦"
            },
            {
                "normalized_label": "١٧٧"
            },
            {
                "normalized_label": "١٧٨"
            },
            {
                "normalized_label": "١٧٩"
            },
            {
                "normalized_label": "١٨٠"
            },
            {
                "normalized_label": "١٨١"
            },
            {
                "normalized_label": "١٨٢"
            },
            {
                "normalized_label": "١٨٣"
            },
            {
                "normalized_label": "١٨٤"
            },
            {
                "normalized_label": "١٨٥"
            },
            {
                "normalized_label": "١٨٦"
            },
            {
                "normalized_label": "١٨٧"
            },
            {
                "normalized_label": "١٨٨"
            },
            {
                "normalized_label": "١٨٩"
            },
            {
                "normalized_label": "١٩٠"
            },
            {
                "normalized_label": "١٩١"
            },
            {
                "normalized_label": "١٩٢"
            },
            {
                "normalized_label": "١٩٣"
            },
            {
                "normalized_label": "١٩٤"
            },
            {
                "normalized_label": "١٩٥"
            },
            {
                "normalized_label": "١٩٦"
            },
            {
                "normalized_label": "١٩٧"
            },
            {
                "normalized_label": "١٩٨"
            },
            {
                "normalized_label": "١٩٩"
            },
            {
                "normalized_label": "٢٠٠"
            },
            {
                "normalized_label": "٢٠١"
            },
            {
                "normalized_label": "٢٠٢"
            },
            {
                "normalized_label": "٢٠٣"
            },
            {
                "normalized_label": "٢٠٤"
            },
            {
                "normalized_label": "٢٠٥"
            },
            {
                "normalized_label": "٢٠٦"
            },
            {
                "normalized_label": "٢٠٧"
            },
            {
                "normalized_label": "٢٠٨"
            },
            {
                "normalized_label": "٢٠٩"
            },
            {
                "normalized_label": "٢١٠"
            },
            {
                "normalized_label": "٢١١"
            },
            {
                "normalized_label": "٢١٢"
            },
            {
                "normalized_label": "٢١٣"
            },
            {
                "normalized_label": "٢١٤"
            },
            {
                "normalized_label": "٢١٥"
            },
            {
                "normalized_label": "٢١٦"
            },
            {
                "normalized_label": "٢١٧"
            },
            {
                "normalized_label": "٢١٨"
            },
            {
                "normalized_label": "٢١٩"
            },
            {
                "normalized_label": "٢٢٠"
            },
            {
                "normalized_label": "٢٢١"
            },
            {
                "normalized_label": "٢٢٢"
            },
            {
                "normalized_label": "٢٢٣"
            },
            {
                "normalized_label": "٢٢٤"
            },
            {
                "normalized_label": "٢٢٥"
            },
            {
                "normalized_label": "٢٢٦"
            },
            {
                "normalized_label": "٢٢٧"
            },
            {
                "normalized_label": "٢٢٨"
            },
            {
                "normalized_label": "٢٢٩"
            },
            {
                "normalized_label": "٢٣٠"
            },
            {
                "normalized_label": "٢٣١"
            },
            {
                "normalized_label": "٢٣٢"
            },
            {
                "normalized_label": "٢٣٣"
            },
            {
                "normalized_label": "٢٣٤"
            },
            {
                "normalized_label": "٢٣٥"
            },
            {
                "normalized_label": "٢٣٦"
            },
            {
                "normalized_label": "٢٣٧"
            },
            {
                "normalized_label": "٢٣٨"
            },
            {
                "normalized_label": "٢٣٩"
            },
            {
                "normalized_label": "٢٤٠"
            },
            {
                "normalized_label": "٢٤١"
            },
            {
                "normalized_label": "٢٤٢"
            },
            {
                "normalized_label": "٢٤٣"
            },
            {
                "normalized_label": "٢٤٥"
            },
            {
                "normalized_label": "٢٤٤"
            },
            {
                "normalized_label": "٢٤٦"
            },
            {
                "normalized_label": "٢٤٧"
            },
            {
                "normalized_label": "٢٤٨"
            },
            {
                "normalized_label": "٢٤٩"
            },
            {
                "normalized_label": "٢٥٠"
            },
            {
                "normalized_label": "٢٥١"
            },
            {
                "normalized_label": "٢٥٢"
            },
            {
                "normalized_label": "٢٥٣"
            },
            {
                "normalized_label": "٢٥٤"
            },
            {
                "normalized_label": "٢٥٥"
            },
            {
                "normalized_label": "٢٥٦"
            },
            {
                "normalized_label": "٢٥٧"
            },
            {
                "normalized_label": "٢٥٨"
            },
            {
                "normalized_label": "٢٥٩"
            },
            {
                "normalized_label": "٢٦٠"
            },
            {
                "normalized_label": "٢٦١"
            },
            {
                "normalized_label": "٢٦٢"
            },
            {
                "normalized_label": "٢٦٣"
            },
            {
                "normalized_label": "٢٦٤"
            },
            {
                "normalized_label": "٢٦٥"
            },
            {
                "normalized_label": "٢٦٦"
            },
            {
                "normalized_label": "٢٦٧"
            },
            {
                "normalized_label": "٢٦٨"
            },
            {
                "normalized_label": "٢٦٩"
            },
            {
                "normalized_label": "٢٧٠"
            },
            {
                "normalized_label": "٢٧١"
            },
            {
                "normalized_label": "٢٧٢"
            },
            {
                "normalized_label": "٢٧٣"
            },
            {
                "normalized_label": "٢٧٥"
            },
            {
                "normalized_label": "٢٧٦"
            },
            {
                "normalized_label": "٢٧٤"
            },
            {
                "normalized_label": "٢٧٧"
            },
            {
                "normalized_label": "٢٧٨"
            },
            {
                "normalized_label": "٢٧٩"
            },
            {
                "normalized_label": "٢٨٠"
            },
            {
                "normalized_label": "٢٨١"
            },
            {
                "normalized_label": "٢٨٢"
            },
            {
                "normalized_label": "٢٨٣"
            },
            {
                "normalized_label": "٢٨٤"
            },
            {
                "normalized_label": "٢٨٥"
            },
            {
                "normalized_label": "٢٨٦"
            },
            {
                "normalized_label": "٢٨٧"
            },
            {
                "normalized_label": "٢٨٩"
            },
            {
                "normalized_label": "٢٩٠"
            },
            {
                "normalized_label": "٢٩١"
            },
            {
                "normalized_label": "٢٩٢"
            },
            {
                "normalized_label": "٢٨٨"
            },
            {
                "normalized_label": "٢٩٣"
            },
            {
                "normalized_label": "٢٩٤"
            },
            {
                "normalized_label": "٢٩٥"
            },
            {
                "normalized_label": "٢٩٦"
            },
            {
                "normalized_label": "٢٩٧"
            },
            {
                "normalized_label": "٢٩٨"
            },
            {
                "normalized_label": "٢٩٩"
            },
            {
                "normalized_label": "٣٠٠"
            },
            {
                "normalized_label": "٣٠١"
            },
            {
                "normalized_label": "٣٠٢"
            },
            {
                "normalized_label": "٣٠٣"
            },
            {
                "normalized_label": "٣٠٤"
            },
            {
                "normalized_label": "٣٠٥"
            },
            {
                "normalized_label": "٣٠٦"
            },
            {
                "normalized_label": "٣٠٧"
            },
            {
                "normalized_label": "٣٠٨"
            },
            {
                "normalized_label": "٣٠٩"
            },
            {
                "normalized_label": "٣١٠"
            },
            {
                "normalized_label": "٣١١"
            },
            {
                "normalized_label": "٣١٢"
            },
            {
                "normalized_label": "٣١٣"
            },
            {
                "normalized_label": "٣١٤"
            },
            {
                "normalized_label": "٣١٥"
            },
            {
                "normalized_label": "٣١٦"
            },
            {
                "normalized_label": "٣١٧"
            },
            {
                "normalized_label": "٣١٨"
            },
            {
                "normalized_label": "٣١٩"
            },
            {
                "normalized_label": "٣٢٠"
            },
            {
                "normalized_label": "٣٢١"
            },
            {
                "normalized_label": "٣٢٢"
            },
            {
                "normalized_label": "٣٢٣"
            },
            {
                "normalized_label": "٣٢٤"
            },
            {
                "normalized_label": "٣٢٥"
            },
            {
                "normalized_label": "٣٢٦"
            },
            {
                "normalized_label": "٣٢٧"
            },
            {
                "normalized_label": "٣٢٨"
            },
            {
                "normalized_label": "٣٢٩"
            },
            {
                "normalized_label": "٣٣٠"
            },
            {
                "normalized_label": "٣٣١"
            },
            {
                "normalized_label": "٣٣٢"
            },
            {
                "normalized_label": "٣٣٣"
            },
            {
                "normalized_label": "٣٣٤"
            },
            {
                "normalized_label": "٣٣٥"
            },
            {
                "normalized_label": "٣٣٦"
            },
            {
                "normalized_label": "٣٣٧"
            },
            {
                "normalized_label": "٣٣٨"
            },
            {
                "normalized_label": "٣٣٩"
            },
            {
                "normalized_label": "٣٤٠"
            },
            {
                "normalized_label": "٣٤١"
            },
            {
                "normalized_label": "٣٤٢"
            },
            {
                "normalized_label": "٣٤٣"
            },
            {
                "normalized_label": "٣٤٤"
            },
            {
                "normalized_label": "٣٤٥"
            },
            {
                "normalized_label": "٣٤٦"
            },
            {
                "normalized_label": "٣٤٧"
            },
            {
                "normalized_label": "٣٤٨"
            },
            {
                "normalized_label": "٣٤٩"
            },
            {
                "normalized_label": "٣٥٠"
            },
            {
                "normalized_label": "٣٥١"
            },
            {
                "normalized_label": "٣٥٢"
            },
            {
                "normalized_label": "٣٥٣"
            },
            {
                "normalized_label": "٣٥٤"
            },
            {
                "normalized_label": "٣٥٥"
            },
            {
                "normalized_label": "٣٥٦"
            },
            {
                "normalized_label": "٣٥٧"
            },
            {
                "normalized_label": "٣٥٨"
            },
            {
                "normalized_label": "٣٥٩"
            },
            {
                "normalized_label": "٣٦٠"
            },
            {
                "normalized_label": "٣٦١"
            },
            {
                "normalized_label": "٣٦٢"
            },
            {
                "normalized_label": "٣٦٣"
            },
            {
                "normalized_label": "٣٦٤"
            },
            {
                "normalized_label": "٣٦٥"
            },
            {
                "normalized_label": "٣٦٦"
            },
            {
                "normalized_label": "٣٦٧"
            },
            {
                "normalized_label": "٣٦٨"
            },
            {
                "normalized_label": "٣٦٩"
            },
            {
                "normalized_label": "٣٧٠"
            },
            {
                "normalized_label": "٣٧١"
            },
            {
                "normalized_label": "٣٧٢"
            },
            {
                "normalized_label": "٣٧٣"
            },
            {
                "normalized_label": "٣٧٤"
            },
            {
                "normalized_label": "٣٧٥"
            },
            {
                "normalized_label": "٣٧٦"
            },
            {
                "normalized_label": "٣٧٧"
            },
            {
                "normalized_label": "٣٧٨"
            },
            {
                "normalized_label": "٣٧٩"
            },
            {
                "normalized_label": "٣٨٠"
            },
            {
                "normalized_label": "٣٨١"
            },
            {
                "normalized_label": "٣٨٢"
            },
            {
                "normalized_label": "٣٨٤"
            },
            {
                "normalized_label": "٣٨٣"
            },
            {
                "normalized_label": "٣٨٥"
            },
            {
                "normalized_label": "٣٨٦"
            },
            {
                "normalized_label": "٣٨٧"
            },
            {
                "normalized_label": "٣٨٨"
            },
            {
                "normalized_label": "٣٨٩"
            },
            {
                "normalized_label": "٣٩٠"
            },
            {
                "normalized_label": "٣٩١"
            },
            {
                "normalized_label": "٣٩٢"
            },
            {
                "normalized_label": "٣٩٣"
            },
            {
                "normalized_label": "٣٩٤"
            },
            {
                "normalized_label": "٣٩٥"
            },
            {
                "normalized_label": "٣٩٦"
            },
            {
                "normalized_label": "٣٩٧"
            },
            {
                "normalized_label": "٣٩٨"
            },
            {
                "normalized_label": "٣٩٩"
            },
            {
                "normalized_label": "٤٠٠"
            },
            {
                "normalized_label": "٤٠١"
            },
            {
                "normalized_label": "٤٠٢"
            },
            {
                "normalized_label": "٤٠٣"
            },
            {
                "normalized_label": "٤٠٤"
            },
            {
                "normalized_label": "٤٠٥"
            },
            {
                "normalized_label": "٤٠٦"
            },
            {
                "normalized_label": "٤٠٧"
            },
            {
                "normalized_label": "٤٠٨"
            },
            {
                "normalized_label": "٤٠٩"
            },
            {
                "normalized_label": "٤١٠"
            },
            {
                "normalized_label": "٤١١"
            },
            {
                "normalized_label": "٤١٢"
            },
            {
                "normalized_label": "٤١٣"
            },
            {
                "normalized_label": "٤١٤"
            },
            {
                "normalized_label": "٤١٥"
            },
            {
                "normalized_label": "٤١٦"
            },
            {
                "normalized_label": "٤١٧"
            },
            {
                "normalized_label": "٤١٨"
            },
            {
                "normalized_label": "٤١٩"
            },
            {
                "normalized_label": "٤٢٠"
            },
            {
                "normalized_label": "٤٢٢"
            },
            {
                "normalized_label": "٤٢١"
            },
            {
                "normalized_label": "٤٢٣"
            },
            {
                "normalized_label": "٤٢٤"
            },
            {
                "normalized_label": "٤٢٥"
            },
            {
                "normalized_label": "٤٢٦"
            },
            {
                "normalized_label": "٤٢٧"
            },
            {
                "normalized_label": "٤٢٨"
            },
            {
                "normalized_label": "٤٢٩"
            },
            {
                "normalized_label": "٤٣٠"
            },
            {
                "normalized_label": "٤٣١"
            },
            {
                "normalized_label": "٤٣٢"
            },
            {
                "normalized_label": "٤٣٣"
            },
            {
                "normalized_label": "٤٣٤"
            },
            {
                "normalized_label": "٤٣٥"
            },
            {
                "normalized_label": "٤٣٦"
            },
            {
                "normalized_label": "٤٣٧"
            },
            {
                "normalized_label": "٤٣٨"
            },
            {
                "normalized_label": "٤٣٩"
            },
            {
                "normalized_label": "٤٤٠"
            },
            {
                "normalized_label": "٤٤١"
            },
            {
                "normalized_label": "٤٤٢"
            },
            {
                "normalized_label": "٤٤٣"
            },
            {
                "normalized_label": "٤٤٤"
            },
            {
                "normalized_label": "٤٤٥"
            },
            {
                "normalized_label": "٤٤٦"
            },
            {
                "normalized_label": "٤٤٧"
            },
            {
                "normalized_label": "٤٤٨"
            },
            {
                "normalized_label": "٤٤٩"
            },
            {
                "normalized_label": "٤٥٠"
            },
            {
                "normalized_label": "٤٥١"
            },
            {
                "normalized_label": "٤٥٢"
            },
            {
                "normalized_label": "٤٥٣"
            },
            {
                "normalized_label": "٤٥٤"
            },
            {
                "normalized_label": "٤٥٥"
            },
            {
                "normalized_label": "٤٥٦"
            },
            {
                "normalized_label": "٤٥٧"
            },
            {
                "normalized_label": "٤٥٨"
            },
            {
                "normalized_label": "٤٥٩"
            },
            {
                "normalized_label": "٤٦٠"
            },
            {
                "normalized_label": "٤٦١"
            },
            {
                "normalized_label": "٤٦٢"
            },
            {
                "normalized_label": "٤٦٣"
            },
            {
                "normalized_label": "٤٦٤"
            },
            {
                "normalized_label": "٤٦٥"
            },
            {
                "normalized_label": "٤٦٦"
            },
            {
                "normalized_label": "٤٦٧"
            },
            {
                "normalized_label": "٤٦٨"
            },
            {
                "normalized_label": "٤٦٩"
            },
            {
                "normalized_label": "٤٧٠"
            },
            {
                "normalized_label": "٤٧١"
            },
            {
                "normalized_label": "٤٧٢"
            },
            {
                "normalized_label": "٤٧٣"
            },
            {
                "normalized_label": "٤٧٤"
            },
            {
                "normalized_label": "٤٧٥"
            },
            {
                "normalized_label": "٤٧٦"
            },
            {
                "normalized_label": "٤٧٧"
            },
            {
                "normalized_label": "٤٧٨"
            },
            {
                "normalized_label": "٤٧٩"
            },
            {
                "normalized_label": "٤٨٠"
            },
            {
                "normalized_label": "٤٨١"
            },
            {
                "normalized_label": "٤٨٢"
            },
            {
                "normalized_label": "٤٨٣"
            },
            {
                "normalized_label": "٤٨٤"
            },
            {
                "normalized_label": "٤٨٥"
            },
            {
                "normalized_label": "٤٨٦"
            },
            {
                "normalized_label": "٤٨٧"
            },
            {
                "normalized_label": "٤٨٨"
            },
            {
                "normalized_label": "٤٨٩"
            },
            {
                "normalized_label": "٤٩٠"
            },
            {
                "normalized_label": "٤٩١"
            },
            {
                "normalized_label": "٤٩٢"
            },
            {
                "normalized_label": "٤٩٣"
            },
            {
                "normalized_label": "٤٩٤"
            },
            {
                "normalized_label": "٤٩٥"
            },
            {
                "normalized_label": "٤٩٦"
            },
            {
                "normalized_label": "٤٩٧"
            },
            {
                "normalized_label": "٤٩٨"
            },
            {
                "normalized_label": "٤٩٩"
            },
            {
                "normalized_label": "٥٠٢"
            },
            {
                "normalized_label": "٥٠٣"
            },
            {
                "normalized_label": "٥٠١"
            },
            {
                "normalized_label": "٥٠٤"
            },
            {
                "normalized_label": "٥٠٠"
            },
            {
                "normalized_label": "٥٠٥"
            },
            {
                "normalized_label": "٥٠٧"
            },
            {
                "normalized_label": "٥٠٨"
            },
            {
                "normalized_label": "٥٠٦"
            },
            {
                "normalized_label": "٥٠٩"
            },
            {
                "normalized_label": "٥١٠"
            },
            {
                "normalized_label": "٥١١"
            },
            {
                "normalized_label": "٥١٢"
            },
            {
                "normalized_label": "٥١٣"
            },
            {
                "normalized_label": "٥١٤"
            },
            {
                "normalized_label": "٥١٥"
            },
            {
                "normalized_label": "٥١٦"
            },
            {
                "normalized_label": "٥١٧"
            },
            {
                "normalized_label": "٥١٨"
            },
            {
                "normalized_label": "٥١٩"
            },
            {
                "normalized_label": "٥٢٠"
            },
            {
                "normalized_label": "٥٢١"
            },
            {
                "normalized_label": "٥٢٢"
            },
            {
                "normalized_label": "٥٢٣"
            },
            {
                "normalized_label": "٥٢٤"
            },
            {
                "normalized_label": "٥٢٥"
            },
            {
                "normalized_label": "٥٢٦"
            },
            {
                "normalized_label": "٥٢٧"
            },
            {
                "normalized_label": "٥٢٨"
            },
            {
                "normalized_label": "٥٢٩"
            },
            {
                "normalized_label": "٥٣٠"
            },
            {
                "normalized_label": "٥٣١"
            },
            {
                "normalized_label": "٥٣٢"
            },
            {
                "normalized_label": "٥٣٣"
            },
            {
                "normalized_label": "٥٣٤"
            },
            {
                "normalized_label": "٥٣٥"
            },
            {
                "normalized_label": "٥٣٦"
            },
            {
                "normalized_label": "٥٣٧"
            },
            {
                "normalized_label": "٥٣٨"
            },
            {
                "normalized_label": "٥٣٩"
            },
            {
                "normalized_label": "٥٤٠"
            },
            {
                "normalized_label": "٥٤١"
            },
            {
                "normalized_label": "٥٤٢"
            },
            {
                "normalized_label": "٥٤٤"
            },
            {
                "normalized_label": "٥٤٣"
            },
            {
                "normalized_label": "٥٤٥"
            },
            {
                "normalized_label": "٥٤٦"
            },
            {
                "normalized_label": "٥٤٧"
            },
            {
                "normalized_label": "٥٤٨"
            },
            {
                "normalized_label": "٥٤٩"
            },
            {
                "normalized_label": "٥٥٠"
            },
            {
                "normalized_label": "٥٥١"
            },
            {
                "normalized_label": "٥٥٢"
            },
            {
                "normalized_label": "٥٥٣"
            },
            {
                "normalized_label": "٥٥٤"
            },
            {
                "normalized_label": "٥٥٥"
            },
            {
                "normalized_label": "٥٥٦"
            },
            {
                "normalized_label": "٥٥٧"
            },
            {
                "normalized_label": "٥٥٨"
            },
            {
                "normalized_label": "٥٥٩"
            },
            {
                "normalized_label": "٥٦٠"
            },
            {
                "normalized_label": "٥٦١"
            },
            {
                "normalized_label": "٥٦٢"
            },
            {
                "normalized_label": "٥٦٣"
            },
            {
                "normalized_label": "٥٦٤"
            },
            {
                "normalized_label": "٥٦٥"
            },
            {
                "normalized_label": "٥٦٦"
            },
            {
                "normalized_label": "٥٦٧"
            },
            {
                "normalized_label": "٥٦٨"
            },
            {
                "normalized_label": "٥٦٩"
            },
            {
                "normalized_label": "٥٧٠"
            },
            {
                "normalized_label": "٥٧١"
            },
            {
                "normalized_label": "٥٧٢"
            },
            {
                "normalized_label": "٥٧٣"
            },
            {
                "normalized_label": "٥٧٤"
            },
            {
                "normalized_label": "٥٧٥"
            },
            {
                "normalized_label": "٥٧٦"
            },
            {
                "normalized_label": "٥٧٧"
            },
            {
                "normalized_label": "٥٧٨"
            },
            {
                "normalized_label": "٥٧٩"
            },
            {
                "normalized_label": "٥٨٠"
            },
            {
                "normalized_label": "٥٨١"
            },
            {
                "normalized_label": "٥٨٢"
            },
            {
                "normalized_label": "٥٨٣"
            },
            {
                "normalized_label": "٥٨٥"
            },
            {
                "normalized_label": "٥٨٤"
            },
            {
                "normalized_label": "٥٨٦"
            },
            {
                "normalized_label": "٥٨٧"
            },
            {
                "normalized_label": "٥٨٨"
            },
            {
                "normalized_label": "٥٨٩"
            },
            {
                "normalized_label": "٥٩٠"
            },
            {
                "normalized_label": "٥٩١"
            },
            {
                "normalized_label": "٥٩٢"
            },
            {
                "normalized_label": "٥٩٣"
            },
            {
                "normalized_label": "٥٩٤"
            },
            {
                "normalized_label": "٥٩٥"
            },
            {
                "normalized_label": "٥٩٦"
            },
            {
                "normalized_label": "٥٩٧"
            },
            {
                "normalized_label": "٥٩٨"
            },
            {
                "normalized_label": "٥٩٩"
            },
            {
                "normalized_label": "٦٠٠"
            },
            {
                "normalized_label": "٦٠١"
            },
            {
                "normalized_label": "٦٠٢"
            },
            {
                "normalized_label": "٦٠٣"
            },
            {
                "normalized_label": "٦٠٤"
            },
            {
                "normalized_label": "٦٠٥"
            },
            {
                "normalized_label": "٦٠٦"
            },
            {
                "normalized_label": "٦٠٧"
            },
            {
                "normalized_label": "٦٠٨"
            },
            {
                "normalized_label": "٦٠٩"
            },
            {
                "normalized_label": "٦١٠"
            },
            {
                "normalized_label": "٦١١"
            },
            {
                "normalized_label": "٦١٢"
            },
            {
                "normalized_label": "٦١٣"
            },
            {
                "normalized_label": "٦١٤"
            },
            {
                "normalized_label": "٦١٥"
            },
            {
                "normalized_label": "٦١٦"
            },
            {
                "normalized_label": "٦١٧"
            },
            {
                "normalized_label": "٦١٨"
            },
            {
                "normalized_label": "٦١٩"
            },
            {
                "normalized_label": "٦٢٠"
            },
            {
                "normalized_label": "٦٢١"
            },
            {
                "normalized_label": "٦٢٢"
            },
            {
                "normalized_label": "٦٢٤"
            },
            {
                "normalized_label": "٦٢٣"
            },
            {
                "normalized_label": "٦٢٥"
            },
            {
                "normalized_label": "٦٢٧"
            },
            {
                "normalized_label": "٦٢٦"
            },
            {
                "normalized_label": "٦٢٨"
            },
            {
                "normalized_label": "٦٢٩"
            },
            {
                "normalized_label": "٦٣٠"
            },
            {
                "normalized_label": "٦٣١"
            },
            {
                "normalized_label": "٦٣٢"
            },
            {
                "normalized_label": "٦٣٣"
            },
            {
                "normalized_label": "٦٣٤"
            },
            {
                "normalized_label": "٦٣٥"
            },
            {
                "normalized_label": "٦٣٦"
            },
            {
                "normalized_label": "٦٣٧"
            },
            {
                "normalized_label": "٦٣٨"
            },
            {
                "normalized_label": "٦٣٩"
            },
            {
                "normalized_label": "٦٤٠"
            },
            {
                "normalized_label": "٦٤١"
            },
            {
                "normalized_label": "٦٤٢"
            },
            {
                "normalized_label": "٦٤٣"
            },
            {
                "normalized_label": "٦٤٤"
            },
            {
                "normalized_label": "٦٤٥"
            },
            {
                "normalized_label": "٦٤٦"
            },
            {
                "normalized_label": "٦٤٧"
            },
            {
                "normalized_label": "٦٤٨"
            },
            {
                "normalized_label": "٦٤٩"
            },
            {
                "normalized_label": "٦٥٠"
            },
            {
                "normalized_label": "٦٥١"
            },
            {
                "normalized_label": "٦٥٢"
            },
            {
                "normalized_label": "٦٥٣"
            },
            {
                "normalized_label": "٦٥٤"
            },
            {
                "normalized_label": "٦٥٥"
            },
            {
                "normalized_label": "٦٥٦"
            },
            {
                "normalized_label": "٦٥٧"
            },
            {
                "normalized_label": "٦٥٨"
            },
            {
                "normalized_label": "٦٥٩"
            },
            {
                "normalized_label": "٦٦٠"
            },
            {
                "normalized_label": "٦٦١"
            },
            {
                "normalized_label": "٦٦٢"
            },
            {
                "normalized_label": "٦٦٣"
            },
            {
                "normalized_label": "٦٦٤"
            },
            {
                "normalized_label": "٦٦٥"
            },
            {
                "normalized_label": "٦٦٦"
            },
            {
                "normalized_label": "٦٦٧"
            },
            {
                "normalized_label": "٦٦٨"
            },
            {
                "normalized_label": "٦٦٩"
            },
            {
                "normalized_label": "٦٧٠"
            },
            {
                "normalized_label": "٦٧١"
            },
            {
                "normalized_label": "٦٧٢"
            },
            {
                "normalized_label": "٦٧٣"
            },
            {
                "normalized_label": "٦٧٤"
            },
            {
                "normalized_label": "٦٧٥"
            },
            {
                "normalized_label": "٦٧٦"
            },
            {
                "normalized_label": "٦٧٧"
            },
            {
                "normalized_label": "٦٧٨"
            },
            {
                "normalized_label": "٦٧٩"
            },
            {
                "normalized_label": "٦٨٠"
            },
            {
                "normalized_label": "٦٨١"
            },
            {
                "normalized_label": "٦٨٣"
            },
            {
                "normalized_label": "٦٨٢"
            },
            {
                "normalized_label": "٦٨٤"
            },
            {
                "normalized_label": "٦٨٥"
            },
            {
                "normalized_label": "٦٨٧"
            },
            {
                "normalized_label": "٦٨٦"
            },
            {
                "normalized_label": "٦٨٨"
            },
            {
                "normalized_label": "٦٨٩"
            },
            {
                "normalized_label": "٦٩٠"
            },
            {
                "normalized_label": "٦٩١"
            },
            {
                "normalized_label": "٦٩٢"
            },
            {
                "normalized_label": "٦٩٣"
            },
            {
                "normalized_label": "٦٩٤"
            },
            {
                "normalized_label": "٦٩٥"
            },
            {
                "normalized_label": "٦٩٦"
            },
            {
                "normalized_label": "٦٩٧"
            },
            {
                "normalized_label": "٦٩٨"
            },
            {
                "normalized_label": "٦٩٩"
            },
            {
                "normalized_label": "٧٠٠"
            },
            {
                "normalized_label": "٧٠١"
            },
            {
                "normalized_label": "٧٠٢"
            },
            {
                "normalized_label": "٧٠٣"
            },
            {
                "normalized_label": "٧٠٤"
            },
            {
                "normalized_label": "٧٠٥"
            },
            {
                "normalized_label": "٧٠٦"
            },
            {
                "normalized_label": "٧٠٧"
            },
            {
                "normalized_label": "٧٠٨"
            },
            {
                "normalized_label": "٧٠٩"
            },
            {
                "normalized_label": "٧١٠"
            },
            {
                "normalized_label": "٧١١"
            },
            {
                "normalized_label": "٧١٢"
            },
            {
                "normalized_label": "٧١٣"
            },
            {
                "normalized_label": "٧١٤"
            },
            {
                "normalized_label": "٧١٥"
            },
            {
                "normalized_label": "٧١٦"
            },
            {
                "normalized_label": "٧١٧"
            },
            {
                "normalized_label": "٧١٨"
            },
            {
                "normalized_label": "٧١٩"
            },
            {
                "normalized_label": "٧٢٠"
            },
            {
                "normalized_label": "٧٢١"
            },
            {
                "normalized_label": "٧٢٢"
            },
            {
                "normalized_label": "٧٢٣"
            },
            {
                "normalized_label": "٧٢٤"
            },
            {
                "normalized_label": "٧٢٥"
            },
            {
                "normalized_label": "٧٢٦"
            },
            {
                "normalized_label": "٧٢٧"
            },
            {
                "normalized_label": "٧٢٨"
            },
            {
                "normalized_label": "٧٢٩"
            },
            {
                "normalized_label": "٧٣٠"
            },
            {
                "normalized_label": "٧٣١"
            },
            {
                "normalized_label": "٧٣٢"
            },
            {
                "normalized_label": "٧٣٣"
            },
            {
                "normalized_label": "٧٣٤"
            },
            {
                "normalized_label": "٧٣٥"
            },
            {
                "normalized_label": "٧٣٦"
            },
            {
                "normalized_label": "٧٣٧"
            },
            {
                "normalized_label": "٧٣٨"
            },
            {
                "normalized_label": "٧٣٩"
            },
            {
                "normalized_label": "٧٤٠"
            },
            {
                "normalized_label": "٧٤١"
            },
            {
                "normalized_label": "٧٤٣"
            },
            {
                "normalized_label": "٧٤٤"
            },
            {
                "normalized_label": "٧٤٥"
            },
            {
                "normalized_label": "٧٤٦"
            },
            {
                "normalized_label": "٧٤٧"
            },
            {
                "normalized_label": "٧٤٨"
            },
            {
                "normalized_label": "٧٤٩"
            },
            {
                "normalized_label": "٧٥٠"
            },
            {
                "normalized_label": "٧٥١"
            },
            {
                "normalized_label": "٧٤٢"
            },
            {
                "normalized_label": "٧٥٢"
            },
            {
                "normalized_label": "٧٥٣"
            },
            {
                "normalized_label": "٧٥٥"
            },
            {
                "normalized_label": "٧٥٦"
            },
            {
                "normalized_label": "٧٥٧"
            },
            {
                "normalized_label": "٧٥٨"
            },
            {
                "normalized_label": "٧٥٩"
            },
            {
                "normalized_label": "٧٥٤"
            },
            {
                "normalized_label": "٧٦٠"
            },
            {
                "normalized_label": "٧٦١"
            },
            {
                "normalized_label": "٧٦٢"
            },
            {
                "normalized_label": "٧٦٣"
            },
            {
                "normalized_label": "٧٦٤"
            },
            {
                "normalized_label": "٧٦٥"
            },
            {
                "normalized_label": "٧٦٦"
            },
            {
                "normalized_label": "٧٦٧"
            },
            {
                "normalized_label": "٧٦٨"
            },
            {
                "normalized_label": "٧٦٩"
            },
            {
                "normalized_label": "٧٧٠"
            },
            {
                "normalized_label": "٧٧١"
            },
            {
                "normalized_label": "٧٧٢"
            },
            {
                "normalized_label": "٧٧٣"
            },
            {
                "normalized_label": "٧٧٤"
            },
            {
                "normalized_label": "٧٧٥"
            },
            {
                "normalized_label": "٧٧٦"
            },
            {
                "normalized_label": "٧٧٧"
            },
            {
                "normalized_label": "٧٧٨"
            },
            {
                "normalized_label": "٧٧٩"
            },
            {
                "normalized_label": "٧٨٠"
            },
            {
                "normalized_label": "٧٨١"
            },
            {
                "normalized_label": "٧٨٢"
            },
            {
                "normalized_label": "٧٨٤"
            },
            {
                "normalized_label": "٧٨٥"
            },
            {
                "normalized_label": "٧٨٦"
            },
            {
                "normalized_label": "٧٨٧"
            },
            {
                "normalized_label": "٧٨٩"
            },
            {
                "normalized_label": "٧٩٠"
            },
            {
                "normalized_label": "٧٩١"
            },
            {
                "normalized_label": "٧٨٣"
            },
            {
                "normalized_label": "٧٨٨"
            },
            {
                "normalized_label": "٧٩٢"
            },
            {
                "normalized_label": "٧٩٣"
            },
            {
                "normalized_label": "٧٩٤"
            },
            {
                "normalized_label": "٧٩٥"
            },
            {
                "normalized_label": "٧٩٦"
            },
            {
                "normalized_label": "٧٩٧"
            },
            {
                "normalized_label": "٧٩٨"
            },
            {
                "normalized_label": "٧٩٩"
            },
            {
                "normalized_label": "٨٠٠"
            },
            {
                "normalized_label": "٨٠١"
            },
            {
                "normalized_label": "٨٠٢"
            },
            {
                "normalized_label": "٨٠٣"
            },
            {
                "normalized_label": "٨٠٤"
            },
            {
                "normalized_label": "٨٠٥"
            },
            {
                "normalized_label": "٨٠٦"
            },
            {
                "normalized_label": "٨٠٧"
            },
            {
                "normalized_label": "٨٠٨"
            },
            {
                "normalized_label": "٨٠٩"
            },
            {
                "normalized_label": "٨١٠"
            },
            {
                "normalized_label": "٨١١"
            },
            {
                "normalized_label": "٨١٢"
            },
            {
                "normalized_label": "٨١٣"
            },
            {
                "normalized_label": "٨١٤"
            },
            {
                "normalized_label": "٨١٥"
            },
            {
                "normalized_label": "٨١٦"
            },
            {
                "normalized_label": "٨١٧"
            },
            {
                "normalized_label": "٨١٨"
            },
            {
                "normalized_label": "٨١٩"
            },
            {
                "normalized_label": "٨٢٠"
            },
            {
                "normalized_label": "٨٢١"
            },
            {
                "normalized_label": "٨٢٣"
            },
            {
                "normalized_label": "٨٢٢"
            },
            {
                "normalized_label": "٨٢٤"
            },
            {
                "normalized_label": "٨٢٥"
            },
            {
                "normalized_label": "٨٢٦"
            },
            {
                "normalized_label": "٨٢٧"
            },
            {
                "normalized_label": "٨٢٨"
            },
            {
                "normalized_label": "٨٢٩"
            },
            {
                "normalized_label": "٨٣٠"
            },
            {
                "normalized_label": "٨٣١"
            },
            {
                "normalized_label": "٨٣٢"
            },
            {
                "normalized_label": "٨٣٣"
            },
            {
                "normalized_label": "٨٣٤"
            },
            {
                "normalized_label": "٨٣٥"
            },
            {
                "normalized_label": "٨٣٦"
            },
            {
                "normalized_label": "٨٣٧"
            },
            {
                "normalized_label": "٨٣٨"
            },
            {
                "normalized_label": "٨٣٩"
            },
            {
                "normalized_label": "٨٤٠"
            },
            {
                "normalized_label": "٨٤١"
            },
            {
                "normalized_label": "٨٤٢"
            },
            {
                "normalized_label": "٨٤٣"
            },
            {
                "normalized_label": "٨٤٤"
            },
            {
                "normalized_label": "٨٤٥"
            },
            {
                "normalized_label": "٨٤٦"
            },
            {
                "normalized_label": "٨٤٧"
            },
            {
                "normalized_label": "٨٤٨"
            },
            {
                "normalized_label": "٨٤٩"
            },
            {
                "normalized_label": "٨٥٠"
            },
            {
                "normalized_label": "٨٥١"
            },
            {
                "normalized_label": "٨٥٢"
            },
            {
                "normalized_label": "٨٥٣"
            },
            {
                "normalized_label": "٨٥٤"
            },
            {
                "normalized_label": "٨٥٥"
            },
            {
                "normalized_label": "٨٥٦"
            },
            {
                "normalized_label": "٨٥٧"
            },
            {
                "normalized_label": "٨٥٨"
            },
            {
                "normalized_label": "٨٥٩"
            },
            {
                "normalized_label": "٨٦٠"
            },
            {
                "normalized_label": "٨٦١"
            },
            {
                "normalized_label": "٨٦٢"
            },
            {
                "normalized_label": "٨٦٣"
            },
            {
                "normalized_label": "٨٦٤"
            },
            {
                "normalized_label": "٨٦٥"
            },
            {
                "normalized_label": "٨٦٦"
            },
            {
                "normalized_label": "٨٦٧"
            },
            {
                "normalized_label": "٨٦٨"
            },
            {
                "normalized_label": "٨٦٩"
            },
            {
                "normalized_label": "٨٧٠"
            },
            {
                "normalized_label": "٨٧١"
            },
            {
                "normalized_label": "٨٧٢"
            },
            {
                "normalized_label": "٨٧٣"
            },
            {
                "normalized_label": "٨٧٤"
            },
            {
                "normalized_label": "٨٧٥"
            },
            {
                "normalized_label": "٨٧٦"
            },
            {
                "normalized_label": "٨٧٧"
            },
            {
                "normalized_label": "٨٧٨"
            },
            {
                "normalized_label": "٨٧٩"
            },
            {
                "normalized_label": "٨٨٠"
            },
            {
                "normalized_label": "٨٨١"
            },
            {
                "normalized_label": "٨٨٣"
            },
            {
                "normalized_label": "٨٨٢"
            },
            {
                "normalized_label": "٨٨٤"
            },
            {
                "normalized_label": "٨٨٥"
            },
            {
                "normalized_label": "٨٨٦"
            },
            {
                "normalized_label": "٨٨٧"
            },
            {
                "normalized_label": "٨٨٩"
            },
            {
                "normalized_label": "٨٨٨"
            },
            {
                "normalized_label": "٨٩٠"
            },
            {
                "normalized_label": "٨٩١"
            },
            {
                "normalized_label": "٨٩٢"
            },
            {
                "normalized_label": "٨٩٣"
            },
            {
                "normalized_label": "٨٩٤"
            },
            {
                "normalized_label": "٨٩٥"
            },
            {
                "normalized_label": "٨٩٦"
            },
            {
                "normalized_label": "٨٩٧"
            },
            {
                "normalized_label": "٨٩٨"
            },
            {
                "normalized_label": "٨٩٩"
            },
            {
                "normalized_label": "٩٠٠"
            },
            {
                "normalized_label": "٩٠١"
            },
            {
                "normalized_label": "٩٠٢"
            },
            {
                "normalized_label": "٩٠٣"
            },
            {
                "normalized_label": "٩٠٤"
            },
            {
                "normalized_label": "٩٠٥"
            },
            {
                "normalized_label": "٩٠٦"
            },
            {
                "normalized_label": "٩٠٧"
            },
            {
                "normalized_label": "٩٠٨"
            },
            {
                "normalized_label": "٩٠٩"
            },
            {
                "normalized_label": "٩١٠"
            },
            {
                "normalized_label": "٩١١"
            },
            {
                "normalized_label": "٩١٢"
            },
            {
                "normalized_label": "٩١٣"
            },
            {
                "normalized_label": "٩١٤"
            },
            {
                "normalized_label": "٩١٥"
            },
            {
                "normalized_label": "٩١٦"
            },
            {
                "normalized_label": "٩١٧"
            },
            {
                "normalized_label": "٩١٨"
            },
            {
                "normalized_label": "٩١٩"
            },
            {
                "normalized_label": "٩٢٠"
            },
            {
                "normalized_label": "٩٢١"
            },
            {
                "normalized_label": "٩٢٢"
            },
            {
                "normalized_label": "٩٢٣"
            },
            {
                "normalized_label": "٩٢٤"
            },
            {
                "normalized_label": "٩٢٥"
            },
            {
                "normalized_label": "٩٢٦"
            },
            {
                "normalized_label": "٩٢٧"
            },
            {
                "normalized_label": "٩٢٨"
            },
            {
                "normalized_label": "٩٢٩"
            },
            {
                "normalized_label": "٩٣٠"
            },
            {
                "normalized_label": "٩٣١"
            },
            {
                "normalized_label": "٩٣٢"
            },
            {
                "normalized_label": "٩٣٣"
            },
            {
                "normalized_label": "٩٣٤"
            },
            {
                "normalized_label": "٩٣٥"
            },
            {
                "normalized_label": "٩٣٦"
            },
            {
                "normalized_label": "٩٣٧"
            },
            {
                "normalized_label": "٩٣٨"
            },
            {
                "normalized_label": "٩٣٩"
            },
            {
                "normalized_label": "٩٤٠"
            },
            {
                "normalized_label": "٩٤١"
            },
            {
                "normalized_label": "٩٤٢"
            },
            {
                "normalized_label": "٩٤٣"
            },
            {
                "normalized_label": "٩٤٤"
            },
            {
                "normalized_label": "٩٤٥"
            },
            {
                "normalized_label": "٩٤٦"
            },
            {
                "normalized_label": "٩٤٧"
            },
            {
                "normalized_label": "٩٤٨"
            },
            {
                "normalized_label": "٩٤٩"
            },
            {
                "normalized_label": "٩٥٠"
            },
            {
                "normalized_label": "٩٥١"
            },
            {
                "normalized_label": "٩٥٢"
            },
            {
                "normalized_label": "٩٥٣"
            },
            {
                "normalized_label": "٩٥٤"
            },
            {
                "normalized_label": "٩٥٥"
            },
            {
                "normalized_label": "٩٥٦"
            },
            {
                "normalized_label": "٩٥٧"
            },
            {
                "normalized_label": "٩٥٨"
            },
            {
                "normalized_label": "٩٥٩"
            },
            {
                "normalized_label": "٩٦٠"
            },
            {
                "normalized_label": "٩٦١"
            },
            {
                "normalized_label": "٩٦٣"
            },
            {
                "normalized_label": "٩٦٢"
            },
            {
                "normalized_label": "٩٦٤"
            },
            {
                "normalized_label": "٩٦٥"
            },
            {
                "normalized_label": "٩٦٦"
            },
            {
                "normalized_label": "٩٦٧"
            },
            {
                "normalized_label": "٩٦٨"
            },
            {
                "normalized_label": "٩٦٩"
            },
            {
                "normalized_label": "٩٧٠"
            },
            {
                "normalized_label": "٩٧١"
            },
            {
                "normalized_label": "٩٧٢"
            },
            {
                "normalized_label": "٩٧٣"
            },
            {
                "normalized_label": "٩٧٤"
            },
            {
                "normalized_label": "٩٧٥"
            },
            {
                "normalized_label": "٩٧٦"
            },
            {
                "normalized_label": "٩٧٧"
            },
            {
                "normalized_label": "٩٧٨"
            },
            {
                "normalized_label": "٩٧٩"
            },
            {
                "normalized_label": "٩٨٠"
            },
            {
                "normalized_label": "٩٨١"
            },
            {
                "normalized_label": "٩٨٢"
            },
            {
                "normalized_label": "٩٨٣"
            },
            {
                "normalized_label": "٩٨٤"
            },
            {
                "normalized_label": "٩٨٥"
            },
            {
                "normalized_label": "٩٨٦"
            },
            {
                "normalized_label": "٩٨٧"
            },
            {
                "normalized_label": "٩٨٨"
            },
            {
                "normalized_label": "٩٨٩"
            },
            {
                "normalized_label": "٩٩٠"
            },
            {
                "normalized_label": "٩٩١"
            },
            {
                "normalized_label": "٩٩٢"
            },
            {
                "normalized_label": "٩٩٣"
            },
            {
                "normalized_label": "٩٩٤"
            },
            {
                "normalized_label": "٩٩٥"
            },
            {
                "normalized_label": "٩٩٦"
            },
            {
                "normalized_label": "٩٩٧"
            },
            {
                "normalized_label": "٩٩٨"
            },
            {
                "normalized_label": "٩٩٩"
            }
        ]
    }
}